hearthgen/__init__.py
hearthgen/paths.py
hearthgen/url.py
hearthgen-0.0.2.dist-info/LICENSE
hearthgen-0.0.2.dist-info/METADATA
hearthgen-0.0.2.dist-info/WHEEL
hearthgen-0.0.2.dist-info/top_level.txt
hearthgen-0.0.2.dist-info/RECORD
