Metadata-Version: 2.1
Name: hearthgen
Version: 0.0.2
Summary: Library to make hearthstone cards in python!
Home-page: https://github.com/h4x4d/hearthgen
Author: h4x4d
Author-email: sidenkoleg@gmail.com
License: UNKNOWN
Platform: UNKNOWN
Classifier: Programming Language :: Python :: 3.9
Classifier: License :: OSI Approved :: MIT License
Classifier: Operating System :: OS Independent
Requires-Python: >=3.6
License-File: LICENSE
Requires-Dist: selenium (>=4.1.1)
Requires-Dist: requests (>=2.27.1)
